elb_log_analyzer/__init__.py
elb_log_analyzer/__main__.py
elb_log_analyzer/alerts.py
elb_log_analyzer/log_analyzer.py
elb_log_analyzer/s3_log.py
elb_log_analyzer/utils.py
elb_log_analyzer-0.5.0.dist-info/LICENSE.md
elb_log_analyzer-0.5.0.dist-info/WHEEL
elb_log_analyzer-0.5.0.dist-info/METADATA
elb_log_analyzer-0.5.0.dist-info/RECORD
